vermeer/__init__.py
vermeer/__pkginfo__.py
vermeer/api.py
vermeer/library.py
vermeer-0.1.0.dist-info/LICENSE
vermeer-0.1.0.dist-info/METADATA
vermeer-0.1.0.dist-info/WHEEL
vermeer-0.1.0.dist-info/entry_points.txt
vermeer-0.1.0.dist-info/top_level.txt
vermeer-0.1.0.dist-info/RECORD
