Metadata-Version: 2.1
Name: vermeer
Version: 0.1.0
Summary: Library and command line tool to handle CK2 portrait files
Home-page: https://github.com/krateng/vermeer
Author: Johannes Krattenmacher
Author-email: misc@krateng.dev
License: GPLv3
Platform: UNKNOWN
Classifier: Programming Language :: Python :: 3
Classifier: License :: OSI Approved :: GNU General Public License v3 (GPLv3)
Classifier: Operating System :: OS Independent
Requires-Python: >=3.5
Requires-Dist: doreah (>=1.4.5)
Requires-Dist: wand (>=0.5.4)
Requires-Dist: pillow (>=7.0.0)
